dsh/__init__.py
dsh/ans.py
dsh/api.py
dsh/evaluators.py
dsh/executors.py
dsh/main.py
dsh/matchers.py
dsh/node.py
dsh/node_factory.py
dsh/shell.py
dsh/data/schema.yml
dsh-2.2.1.dist-info/LICENSE.txt
dsh-2.2.1.dist-info/METADATA
dsh-2.2.1.dist-info/WHEEL
dsh-2.2.1.dist-info/entry_points.txt
dsh-2.2.1.dist-info/top_level.txt
dsh-2.2.1.dist-info/RECORD
