Metadata-Version: 2.1
Name: dsh
Version: 2.2.1
Summary: console application to organize commands and environments
Home-page: https://github.com/flashashen/dsh2
Author: flashashen
Author-email: flashashen@gmail.com
License: MIT
Keywords: shell console yaml
Platform: osx
Platform: linux
Classifier: License :: OSI Approved :: MIT License
Classifier: Programming Language :: Python
Classifier: Programming Language :: Python :: 3
Classifier: Programming Language :: Python :: 3.6
Classifier: Programming Language :: Python :: 3.7
Classifier: Programming Language :: Python :: 3.8
Classifier: Programming Language :: Python :: 3.9
Classifier: Programming Language :: Python :: 3.10
Classifier: Topic :: Software Development
Classifier: Environment :: Console
Classifier: Operating System :: MacOS
Classifier: Operating System :: POSIX :: Linux
Classifier: Development Status :: 3 - Alpha
License-File: LICENSE.txt
